odoo/addons/sale_order_priority/README.rst
odoo/addons/sale_order_priority/__init__.py
odoo/addons/sale_order_priority/__manifest__.py
odoo/addons/sale_order_priority/i18n/es.po
odoo/addons/sale_order_priority/i18n/it.po
odoo/addons/sale_order_priority/i18n/sale_order_priority.pot
odoo/addons/sale_order_priority/migrations/14.0.1.0.0/post-migration.py
odoo/addons/sale_order_priority/migrations/14.0.1.0.0/pre-migration.py
odoo/addons/sale_order_priority/models/__init__.py
odoo/addons/sale_order_priority/models/sale.py
odoo/addons/sale_order_priority/models/stock_picking.py
odoo/addons/sale_order_priority/readme/CONTRIBUTORS.rst
odoo/addons/sale_order_priority/readme/DESCRIPTION.rst
odoo/addons/sale_order_priority/static/description/icon.png
odoo/addons/sale_order_priority/static/description/index.html
odoo/addons/sale_order_priority/tests/__init__.py
odoo/addons/sale_order_priority/tests/test_sale_stock.py
odoo/addons/sale_order_priority/views/sale.xml
odoo14_addon_sale_order_priority-14.0.1.0.1.dev10.dist-info/METADATA
odoo14_addon_sale_order_priority-14.0.1.0.1.dev10.dist-info/WHEEL
odoo14_addon_sale_order_priority-14.0.1.0.1.dev10.dist-info/top_level.txt
odoo14_addon_sale_order_priority-14.0.1.0.1.dev10.dist-info/RECORD
